{
    "嵌入標題":"問答小遊戲",
    "按鈕回覆內容":"嗨",

    "每題間隔秒數":"5",
    "遊戲統計訊息傳送頻道ID":"1026902773398241400",

    "問答集":
    [
    {"題目":"每週最多可以透過狩獵討伐和居民請求，獲得共多少點聲望經驗？","答案":"C","圖片網址":"https://cdn.discordapp.com/attachments/1006891319903404092/1027231794925416518/unknown.png","A":"400","B":"450","C":"420","D":"390"},
    {"題目":"消耗品「四方八方之網」的購買價格為？","答案":"B","圖片網址":"","A":"1個7500摩拉","B":"1個10000摩拉","C":"1個5000摩拉","D":"1個20000摩拉"},
    {"題目":"1+1=","答案":"A","圖片網址":"","A":"1","B":"2","C":"3","D":"4"},
    {"題目":"2+2=","答案":"D","圖片網址":"","A":"1","B":"2","C":"3","D":"4"}
    ]

}